{"date":"2024-06-05T14:37:45.205Z","courseId":"17","assignment":"AP-Spring03-CA6","trace":{"version":288,"content":"#include \"superCommands.hpp\"\n\nSuperCommand::SuperCommand(string inputSuperCommand , string inputSeprator)\n{\n\n}\n\nbool SuperCommand::CheckSuperCommandAndSeprator(string inputSuperCommand , string inputSeprator)\n{\n    for (int i = 0 ; i < superCommandsList.size(); i++)\n    {\n        if (inputSuperCommand == superCommandsList[i] && )\n        {\n            return true;\n        }\n    }\n    return false;\n}","filename":"/home/rayan/Desktop/clone/AP-FinalPraject/superCommands.cpp","identifier":"Text Change","lineCount":18,"languageId":"cpp"},"failed":false}